{"id": "3658", "title": "Bug 3658JDT change listener efficiency issue (1GEMN5F)", "description": "Bug 3658JDT change listener efficiency issue (1GEMN5F) ", "OB": "ClassFileMarkerAnnotationModel.visit is very much less than optimal if fMarkerResource is set.It traverses the entire delta only looking for a particular resource!I don't understand when fMarkerResourceis set and when it is not but in the case I saw, it was set to be a particular project resource which was noteven in the list of resources which changed in the large delta I was processing.The net result ofthis was that the listener traversed the entire delta (~1500 resources) checking at each node to seeif the node was equal to fMarkerResource.Since the listener knows that it is only interested in that one resource, it should just take the deltaand look in it to see if the resource in question is there.The current IResourceDelta api is notoptimal for doing this but it certainly can be done and would be very much more efficient than thecurrent approach.We will look at adding the required API but this late in the game I would not hopefor too much.NOTES:JBL (6/1/2001 11:47:09 AM)ClassFileMarkerAnnotationModel is JUI.Moving to ITPJUI.KUM (8/6/2001 4:41:57 PM)Sent mail to JMA regarding expected core support. ", "EB": "", "SR": ""}