{"id": "9112", "title": "Bug 9112goto type presents items not visible", "description": "", "OB": "Bug 9112goto type presents items not visible stable 20020125In the packages viewChoose Go ToTypefrom the popupThe resulting dialog displays things you cannot go to it shows classes in referenced libraries even if you are not currenrtlyshowing referenced libraries it shows classes not in your working setAs a result if you pick that class nothing actually happens and you don't knowwhy.Some options (food for thought): filter the dialog (classes in current view vs. all classes) let the user pick it then warn him its not in his current view and offer tochange the view ", "EB": "", "SR": ""}