{"id": "8757", "title": "Bug 8757Type Hierarchy view  Error decoration not removed when error fixed", "description": " Bug 8757Type Hierarchy viewError decoration not removed when error fixed", "OB": "", "EB": "", "SR": " Eclipse 200201129IWindows 20001) Focus on the hierarchy of class (one that has a few super classes).2) Cause a compile error to happen in the class and save the change.3) Select a different class in the hierarchy and then select the class withthe error.Note that now the label at the top of the methods list in theTypeHierarchy view nows has a red x on it.I don't know why you have to flipbetween classes to make this red x appearit should appear as soon as yousave the change that caused a compile error.4) Now fix the compile error and save the change.The red x does not disappearfrom the label above the methods list."}