{"code": 200, "status": "success", "bug_report": {"0": {"text": "Bug 8280  Package view back/forward/up arrow hover help.", "labels": []}, "1": {"text": "Start up Eclipse with some existing Java Projects in the workspace.", "labels": ["OB", "SR"]}, "2": {"text": "Select a package in one of these projects.", "labels": ["SR"]}, "3": {"text": "Right-click and select Go Into.", "labels": ["SR"]}, "4": {"text": "Hover over the Back arrow.", "labels": ["SR"]}, "5": {"text": "Notice that a very tall tool-tip (full screen height) text appears, the first line being \"Back to Java Model\" and the remaining lines being package names (?).", "labels": ["OB"]}, "6": {"text": "Immediately after being displayed, the tool-tip text disappears.", "labels": ["OB"]}, "7": {"text": "The text will flash into and out of existance consitently until the pointer leaves the button's frame.", "labels": ["OB", "EB"]}, "8": {"text": "The same behaviour can occur when hovering over the Up arrow or the Forward arrow when these lead to the workspace root.", "labels": ["OB", "EB"]}}}