{"id": "12779", "title": "Bug 12779(0321) Workbench silently catching exceptions and removing listeners", "description": " Bug 12779(0321) Workbench silently catching exceptions and removing listeners", "OB": " In SafeRunnable.handleException(Throwable e), there is a boolean check that isinverted.Instead of showing Errors, it NEVER shows errors.As a result, I had my ISelectionListener silently removed from the selectionservice.Also, I got into a state where the JDT's F4 action stopped followingselection, and kept opening a hierarachy on the same class (the last one theywere notified about before throwing an exception).", "EB": "", "SR": ""}