{"id": "125084", "title": "Bug 125084o option does not work when generating PDF with ReportRunner", "description": " My command line looks like this:%JAVACMD% cp \"%BIRTCLASSPATH%\" DBIRTHOME=\"%BIRTHOME%\\Report Engine\" org.eclipse.birt.report.engine.api.ReportRunnerfPDF o outputpdfTest.rptdesignIt would seem there is no way to specify the name of the output pdf file, I need different outputs for different parameters.I get the stacktrace below:WARNING: output\\pdfTest.PDF (The system cannot find the path specified)java.io.FileNotFoundException: output\\pdfTest.PDF (The system cannot find the path specified)at java.io.FileOutputStream.open(Native Method)at java.io.FileOutputStream.<init(FileOutputStream.java:179)at java.io.FileOutputStream.<init(FileOutputStream.java:131)at org.eclipse.birt.report.engine.emitter.pdf.PDFEmitter.initialize(PDFEmitter.java:172)at org.eclipse.birt.report.engine.layout.impl.ReportLayoutEngine.initialize(ReportLayoutEngine.java:415)at org.eclipse.birt.report.engine.presentation.WrappedEmitter.initialize(WrappedEmitter.java:44)at org.eclipse.birt.report.engine.presentation.LocalizedEmitter.initialize(LocalizedEmitter.java:129)at org.eclipse.birt.report.engine.api.impl.RunAndRenderTask.createContentEmitter(RunAndRenderTask.java:145)at org.eclipse.birt.report.engine.api.impl.RunAndRenderTask.run(RunAndRenderTask.java:174)at org.eclipse.birt.report.engine.api.ReportRunner.runAndRenderReport(ReportRunner.java:232)at org.eclipse.birt.report.engine.api.ReportRunner.execute(ReportRunner.java:158)at org.eclipse.birt.report.engine.api.ReportRunner.main(ReportRunner.java:129)", "OB": " Bug 125084o option does not work when generating PDF with ReportRunner", "EB": "", "SR": ""}