{"id": "134216", "title": "Bug 134216[regression] add a report item to library does not work properly", "description": " Bug 134216[regression] add a report item to library does not work properly", "OB": "", "EB": "", "SR": " steps to reproduce: create a library add report items, say label add 1st label add 2nd laeblexpected behavior: everytime i drag a label to OutlineReportItems, the label will be addedactual behavior: for the 1st label, it worked out fine for the 2nd label, i had to drag a label twice to complete the operationnote that this happened with other report items as well"}