{"id": "27378", "title": "Bug 27378[startup] [Editor Mgmt] junit view loaded even though it's a hidden fast view", "description": "Bug 27378[startup] [Editor Mgmt] junit view loaded even though it's a hidden fast view which loads the whole pluginstacktrace from core tools:Activating plugin: org.eclipse.jdt.junitPlugin activation stack:org.eclipse.jdt.junitClass loading stack:Stack trace:java.lang.Throwableat java.lang.Throwable.<init(Unknown Source)at org.eclipse.core.internal.runtime.PluginStats.traceActivate(UnknownSource)at org.eclipse.core.internal.runtime.PluginStats.startActivation(Unknown Source)at org.eclipse.core.internal.plugins.PluginDescriptor.doPluginActivation(Unknown Source)at org.eclipse.core.internal.plugins.PluginClassLoader.activatePlugin(Unknown Source)atorg.eclipse.core.internal.plugins.PluginClassLoader.internalFindClassParentsSelf(Unknown Source)atorg.eclipse.core.internal.boot.DelegatingURLClassLoader.findClassParentsSelf(Unknown Source)at org.eclipse.core.internal.boot.DelegatingURLClassLoader.loadClass(Unknown Source)at org.eclipse.core.internal.boot.DelegatingURLClassLoader.loadClass(Unknown Source)at java.lang.ClassLoader.loadClass(Unknown Source)atorg.eclipse.core.internal.plugins.PluginDescriptor.createExecutableExtension(Unknown Source)atorg.eclipse.core.internal.plugins.PluginDescriptor.createExecutableExtension(Unknown Source)atorg.eclipse.core.internal.plugins.ConfigurationElement.createExecutableExtension(Unknown Source)at org.eclipse.ui.internal.WorkbenchPlugin$1.run(Unknown Source)at org.eclipse.swt.custom.BusyIndicator.showWhile(Unknown Source)at org.eclipse.ui.internal.WorkbenchPlugin.createExtension(UnknownSource)at org.eclipse.ui.internal.registry.ViewDescriptor.createView(UnknownSource)at org.eclipse.ui.internal.ViewFactory$2.run(Unknown Source)at org.eclipse.core.internal.runtime.InternalPlatform.run(UnknownSource)at org.eclipse.core.runtime.Platform.run(Unknown Source)at org.eclipse.ui.internal.ViewFactory.busyRestoreView(Unknown Source)at org.eclipse.ui.internal.ViewFactory$1.run(Unknown Source)at org.eclipse.swt.custom.BusyIndicator.showWhile(Unknown Source)at org.eclipse.ui.internal.ViewFactory.restoreView(Unknown Source)at org.eclipse.ui.internal.Perspective.restoreState(Unknown Source)at org.eclipse.ui.internal.WorkbenchPage.restoreState(Unknown Source)at org.eclipse.ui.internal.WorkbenchWindow.restoreState(Unknown Source)at org.eclipse.ui.internal.Workbench.restoreState(Unknown Source)at org.eclipse.ui.internal.Workbench.access$7(Unknown Source)at org.eclipse.ui.internal.Workbench$8.run(Unknown Source)at org.eclipse.core.internal.runtime.InternalPlatform.run(UnknownSource)at org.eclipse.core.runtime.Platform.run(Unknown Source)at org.eclipse.ui.internal.Workbench.openPreviousWorkbenchState(UnknownSource)at org.eclipse.ui.internal.Workbench.init(Unknown Source)at org.eclipse.ui.internal.Workbench.run(Unknown Source)at org.eclipse.core.internal.boot.InternalBootLoader.run(Unknown Source)at org.eclipse.core.boot.BootLoader.run(Unknown Source)at java.lang.reflect.AccessibleObject.invokeL(Unknown Source)at java.lang.reflect.Method.invoke(Unknown Source)at org.eclipse.core.launcher.Main.basicRun(Unknown Source)at org.eclipse.core.launcher.Main.run(Unknown Source)at org.eclipse.core.launcher.Main.main(Unknown Source) ", "OB": "20021127the junit view is a collapsed fast viewbut it is loaded on startup anyway,. ", "EB": "", "SR": ""}