{"id": "44174", "title": "Bug 44174Eclipse crashes using SWT Designer plugin", "description": "Bug 44174Eclipse crashes using SWT Designer plugin ", "OB": "I20030930Trying to take a look at Instantiations' SWT Designer, Eclipse immediately exits when switching itsdesign perspective. The crash log of MacOS X contains the follwing output:Thread 0 Crashed: 00x969e962c in TestWindowGroupAttributes 10x969eb71c in HiliteAndActivateWindow 20x96a0a380 inZ27AdjustToNewWindowActivationP10WindowDataP13WindowContextP15OpaqueWindowPtrS0 30x96a58518 in Z36PotentiallyAdjustActivationOnOrderInP10WindowDataS0 40x96a49ffc in ShowWindow 50x046a1ab0 in JavaorgeclipseswtinternalcarbonOSShowWindow [...] ", "EB": "", "SR": "I20030930Trying to take a look at Instantiations' SWT Designer, Eclipse immediately exits when switching itsdesign perspective. "}